pyzehndercloud/__init__.py
pyzehndercloud/auth.py
pyzehndercloud/zehndercloud.py
pyzehndercloud-0.1.dist-info/WHEEL
pyzehndercloud-0.1.dist-info/METADATA
pyzehndercloud-0.1.dist-info/RECORD
