Metadata-Version: 2.1
Name: pyzehndercloud
Version: 0.1
Summary: 
Author: Michaël Arnauts
Author-email: michael.arnauts@gmail.com
Requires-Python: >=3.10,<4.0
Classifier: Programming Language :: Python :: 3
Classifier: Programming Language :: Python :: 3.10
Classifier: Programming Language :: Python :: 3.11
Requires-Dist: aiohttp (>=3.8.1,<3.9.0)
Requires-Dist: msal (>=1.18.0,<1.19.0)
